plantdrppred/blast_binaries/linux/blastp
plantdrppred/blast_binaries/linux/psiblast
plantdrppred/blast_binaries/mac/blastp
plantdrppred/blast_binaries/mac/psiblast
plantdrppred/blast_binaries/windows/blastp.exe
plantdrppred/blast_binaries/windows/ncbi-vdb-md.dll
plantdrppred/blast_binaries/windows/nghttp2.dll
plantdrppred/blast_binaries/windows/psiblast.exe
plantdrppred/blastdb/train.pdb
plantdrppred/blastdb/train.phr
plantdrppred/blastdb/train.pin
plantdrppred/blastdb/train.pjs
plantdrppred/blastdb/train.pog
plantdrppred/blastdb/train.pos
plantdrppred/blastdb/train.pot
plantdrppred/blastdb/train.psq
plantdrppred/blastdb/train.ptf
plantdrppred/blastdb/train.pto
plantdrppred/model/model_aac
plantdrppred/model/model_pssm
plantdrppred/possum/featureGenerator.py
plantdrppred/possum/featureGenerator.pyc
plantdrppred/possum/headerHandler.py
plantdrppred/possum/matrixTransformer.py
plantdrppred/possum/matrixTransformer.pyc
plantdrppred/possum/possum.py
plantdrppred/possum/possum_ft.py
plantdrppred/possum/possum_ft.pyc
plantdrppred/python_scripts/__init__.py
plantdrppred/python_scripts/plantdrppred.py
plantdrppred-1.7.dist-info/LICENSE
plantdrppred-1.7.dist-info/METADATA
plantdrppred-1.7.dist-info/WHEEL
plantdrppred-1.7.dist-info/entry_points.txt
plantdrppred-1.7.dist-info/top_level.txt
plantdrppred-1.7.dist-info/RECORD
