Metadata-Version: 2.1
Name: plantdrppred
Version: 1.7
Summary: A tool to predict Plant Diesease Resistance Protein
Home-page: https://github.com/raghavagps/plantdrppred
Author: Gajendra P.S. Raghava
Author-email: raghava@iiitd.ac.in
Requires-Python: >=3.8
License-File: LICENSE
Requires-Dist: numpy
Requires-Dist: pandas
Requires-Dist: scikit-learn <=1.3.2,>=1.3.0
Requires-Dist: argparse
Requires-Dist: biopython
Requires-Dist: requests
